{
  "timestamp": "2026-03-04T14:56:52.160378",
  "label": "paper_final",
  "config_path": "experiments/configs/paper_final.yaml",
  "jsonl_path": "experiments/results/phase2_patha_scale500_gain_predictor/patha_agent_outputs_20260304_080157.jsonl",
  "n_samples": 1500,
  "seeds": [
    300,
    301,
    302,
    303,
    304,
    305,
    306,
    307,
    308,
    309
  ],
  "trust_scores": {
    "frequency": 0.85,
    "noise": 0.8,
    "fatformer": 0.85,
    "spatial": 0.85
  },
  "results_per_seed": [
    {
      "majority_vote": 0.27492063492063495,
      "weighted_mv": 0.2679873349245971,
      "cobra": 0.26127897967697716,
      "logistic_stacking": 0.8536343830461477,
      "daac_logistic_regression": 0.8565867258456418,
      "daac_gradient_boosting": 0.8562054234097246,
      "daac_mlp": 0.8675056689342404,
      "abl_A1_confidence_only": 0.7880097090830455,
      "abl_A2_verdict_only": 0.789792592266359,
      "abl_A3_disagreement_only": 0.8463889296060624,
      "abl_A4_verdict_confidence": 0.8562593418338803,
      "abl_A5_full": 0.8562054234097246
    },
    {
      "majority_vote": 0.2796945613214898,
      "weighted_mv": 0.2666630183426506,
      "cobra": 0.27123472845846425,
      "logistic_stacking": 0.8316059221239204,
      "daac_logistic_regression": 0.8417747855155809,
      "daac_gradient_boosting": 0.8470392869438749,
      "daac_mlp": 0.83518772178566,
      "abl_A1_confidence_only": 0.7618785165463718,
      "abl_A2_verdict_only": 0.7532520325203252,
      "abl_A3_disagreement_only": 0.847296494355318,
      "abl_A4_verdict_confidence": 0.840786851622506,
      "abl_A5_full": 0.8470392869438749
    },
    {
      "majority_vote": 0.2775707989383203,
      "weighted_mv": 0.2444105403929103,
      "cobra": 0.25345176873928627,
      "logistic_stacking": 0.8480478452383632,
      "daac_logistic_regression": 0.8515101438651227,
      "daac_gradient_boosting": 0.8698722212497811,
      "daac_mlp": 0.8515101438651227,
      "abl_A1_confidence_only": 0.795823199579068,
      "abl_A2_verdict_only": 0.7753836813308932,
      "abl_A3_disagreement_only": 0.8467860119345268,
      "abl_A4_verdict_confidence": 0.8321942947705759,
      "abl_A5_full": 0.8698722212497811
    },
    {
      "majority_vote": 0.31246499622567997,
      "weighted_mv": 0.2776417399675569,
      "cobra": 0.27051824964710625,
      "logistic_stacking": 0.8680914431999359,
      "daac_logistic_regression": 0.8680914431999359,
      "daac_gradient_boosting": 0.8370031871977252,
      "daac_mlp": 0.8680914431999359,
      "abl_A1_confidence_only": 0.8019647462750316,
      "abl_A2_verdict_only": 0.7267121479401424,
      "abl_A3_disagreement_only": 0.8408541967917529,
      "abl_A4_verdict_confidence": 0.8432964157437269,
      "abl_A5_full": 0.8370031871977252
    },
    {
      "majority_vote": 0.26442262739597944,
      "weighted_mv": 0.25457118467789824,
      "cobra": 0.2641455195429571,
      "logistic_stacking": 0.8385159922905571,
      "daac_logistic_regression": 0.8415515594757657,
      "daac_gradient_boosting": 0.8562458144409094,
      "daac_mlp": 0.8548179678614461,
      "abl_A1_confidence_only": 0.7920915783075572,
      "abl_A2_verdict_only": 0.7280788982452467,
      "abl_A3_disagreement_only": 0.8495656203812721,
      "abl_A4_verdict_confidence": 0.8328979414806659,
      "abl_A5_full": 0.8562458144409094
    },
    {
      "majority_vote": 0.2899283607248209,
      "weighted_mv": 0.27328502226834245,
      "cobra": 0.2777102599753345,
      "logistic_stacking": 0.8248748714947135,
      "daac_logistic_regression": 0.8483858148070226,
      "daac_gradient_boosting": 0.8672720352799589,
      "daac_mlp": 0.8375451143173881,
      "abl_A1_confidence_only": 0.8101181320693516,
      "abl_A2_verdict_only": 0.774159331584086,
      "abl_A3_disagreement_only": 0.8599868431255331,
      "abl_A4_verdict_confidence": 0.8671496394132046,
      "abl_A5_full": 0.8672720352799589
    },
    {
      "majority_vote": 0.2737826021408111,
      "weighted_mv": 0.2721716182751143,
      "cobra": 0.27279492265398936,
      "logistic_stacking": 0.8673495703199886,
      "daac_logistic_regression": 0.8606214110264672,
      "daac_gradient_boosting": 0.8937132519222072,
      "daac_mlp": 0.8640221852323879,
      "abl_A1_confidence_only": 0.8161529124138757,
      "abl_A2_verdict_only": 0.7669490282361568,
      "abl_A3_disagreement_only": 0.8733449060467428,
      "abl_A4_verdict_confidence": 0.8933189281127426,
      "abl_A5_full": 0.8937132519222072
    },
    {
      "majority_vote": 0.2578417047761817,
      "weighted_mv": 0.26629712417023726,
      "cobra": 0.25938501335872266,
      "logistic_stacking": 0.8502910592566795,
      "daac_logistic_regression": 0.86035336301008,
      "daac_gradient_boosting": 0.8669314232855821,
      "daac_mlp": 0.8640797865417155,
      "abl_A1_confidence_only": 0.7990726817042607,
      "abl_A2_verdict_only": 0.7438672438672439,
      "abl_A3_disagreement_only": 0.849017317556244,
      "abl_A4_verdict_confidence": 0.8536411430087733,
      "abl_A5_full": 0.8669314232855821
    },
    {
      "majority_vote": 0.25151647406339145,
      "weighted_mv": 0.2534768284100322,
      "cobra": 0.25506812894649383,
      "logistic_stacking": 0.8735982566230822,
      "daac_logistic_regression": 0.8604674192909488,
      "daac_gradient_boosting": 0.8674510931626284,
      "daac_mlp": 0.8666285496474176,
      "abl_A1_confidence_only": 0.8058033049976179,
      "abl_A2_verdict_only": 0.7770868347338936,
      "abl_A3_disagreement_only": 0.8665506202480993,
      "abl_A4_verdict_confidence": 0.8609282947628812,
      "abl_A5_full": 0.8674510931626284
    },
    {
      "majority_vote": 0.2921396521210604,
      "weighted_mv": 0.2879349605010828,
      "cobra": 0.27849867083642094,
      "logistic_stacking": 0.844295227589749,
      "daac_logistic_regression": 0.8511901470675927,
      "daac_gradient_boosting": 0.8509799959587796,
      "daac_mlp": 0.8608135791630085,
      "abl_A1_confidence_only": 0.8008844621314637,
      "abl_A2_verdict_only": 0.761000400160064,
      "abl_A3_disagreement_only": 0.8539881717545192,
      "abl_A4_verdict_confidence": 0.8255718954248366,
      "abl_A5_full": 0.8509799959587796
    }
  ],
  "aggregated": {
    "majority_vote": {
      "mean": 0.277428241262837,
      "std": 0.017792589533596262,
      "runs": [
        0.27492063492063495,
        0.2796945613214898,
        0.2775707989383203,
        0.31246499622567997,
        0.26442262739597944,
        0.2899283607248209,
        0.2737826021408111,
        0.2578417047761817,
        0.25151647406339145,
        0.2921396521210604
      ]
    },
    "weighted_mv": {
      "mean": 0.2664439371930422,
      "std": 0.012753613908696969,
      "runs": [
        0.2679873349245971,
        0.2666630183426506,
        0.2444105403929103,
        0.2776417399675569,
        0.25457118467789824,
        0.27328502226834245,
        0.2721716182751143,
        0.26629712417023726,
        0.2534768284100322,
        0.2879349605010828
      ]
    },
    "cobra": {
      "mean": 0.26640862418357525,
      "std": 0.0090192032866748,
      "runs": [
        0.26127897967697716,
        0.27123472845846425,
        0.25345176873928627,
        0.27051824964710625,
        0.2641455195429571,
        0.2777102599753345,
        0.27279492265398936,
        0.25938501335872266,
        0.25506812894649383,
        0.27849867083642094
      ]
    },
    "logistic_stacking": {
      "mean": 0.8500304571183138,
      "std": 0.016111837453338374,
      "runs": [
        0.8536343830461477,
        0.8316059221239204,
        0.8480478452383632,
        0.8680914431999359,
        0.8385159922905571,
        0.8248748714947135,
        0.8673495703199886,
        0.8502910592566795,
        0.8735982566230822,
        0.844295227589749
      ]
    },
    "daac_logistic_regression": {
      "mean": 0.8540532813104159,
      "std": 0.008700578678149244,
      "runs": [
        0.8565867258456418,
        0.8417747855155809,
        0.8515101438651227,
        0.8680914431999359,
        0.8415515594757657,
        0.8483858148070226,
        0.8606214110264672,
        0.86035336301008,
        0.8604674192909488,
        0.8511901470675927
      ]
    },
    "daac_gradient_boosting": {
      "mean": 0.8612713732851172,
      "std": 0.015567104911996867,
      "runs": [
        0.8562054234097246,
        0.8470392869438749,
        0.8698722212497811,
        0.8370031871977252,
        0.8562458144409094,
        0.8672720352799589,
        0.8937132519222072,
        0.8669314232855821,
        0.8674510931626284,
        0.8509799959587796
      ]
    },
    "daac_mlp": {
      "mean": 0.8570202160548324,
      "std": 0.012152913527411534,
      "runs": [
        0.8675056689342404,
        0.83518772178566,
        0.8515101438651227,
        0.8680914431999359,
        0.8548179678614461,
        0.8375451143173881,
        0.8640221852323879,
        0.8640797865417155,
        0.8666285496474176,
        0.8608135791630085
      ]
    },
    "abl_A1_confidence_only": {
      "mean": 0.7971799243107643,
      "std": 0.014906929964868611,
      "runs": [
        0.7880097090830455,
        0.7618785165463718,
        0.795823199579068,
        0.8019647462750316,
        0.7920915783075572,
        0.8101181320693516,
        0.8161529124138757,
        0.7990726817042607,
        0.8058033049976179,
        0.8008844621314637
      ]
    },
    "abl_A2_verdict_only": {
      "mean": 0.7596282190884411,
      "std": 0.021337106693266772,
      "runs": [
        0.789792592266359,
        0.7532520325203252,
        0.7753836813308932,
        0.7267121479401424,
        0.7280788982452467,
        0.774159331584086,
        0.7669490282361568,
        0.7438672438672439,
        0.7770868347338936,
        0.761000400160064
      ]
    },
    "abl_A3_disagreement_only": {
      "mean": 0.853377911180007,
      "std": 0.010197635549989275,
      "runs": [
        0.8463889296060624,
        0.847296494355318,
        0.8467860119345268,
        0.8408541967917529,
        0.8495656203812721,
        0.8599868431255331,
        0.8733449060467428,
        0.849017317556244,
        0.8665506202480993,
        0.8539881717545192
      ]
    },
    "abl_A4_verdict_confidence": {
      "mean": 0.8506044746173792,
      "std": 0.020207057789558808,
      "runs": [
        0.8562593418338803,
        0.840786851622506,
        0.8321942947705759,
        0.8432964157437269,
        0.8328979414806659,
        0.8671496394132046,
        0.8933189281127426,
        0.8536411430087733,
        0.8609282947628812,
        0.8255718954248366
      ]
    },
    "abl_A5_full": {
      "mean": 0.8612713732851172,
      "std": 0.015567104911996867,
      "runs": [
        0.8562054234097246,
        0.8470392869438749,
        0.8698722212497811,
        0.8370031871977252,
        0.8562458144409094,
        0.8672720352799589,
        0.8937132519222072,
        0.8669314232855821,
        0.8674510931626284,
        0.8509799959587796
      ]
    }
  },
  "pvalues_vs_cobra": {
    "majority_vote": 0.037109375,
    "weighted_mv": 1.0,
    "cobra": NaN,
    "logistic_stacking": 0.001953125,
    "daac_logistic_regression": 0.001953125,
    "daac_gradient_boosting": 0.001953125,
    "daac_mlp": 0.001953125,
    "abl_A1_confidence_only": 0.001953125,
    "abl_A2_verdict_only": 0.001953125,
    "abl_A3_disagreement_only": 0.001953125,
    "abl_A4_verdict_confidence": 0.001953125,
    "abl_A5_full": 0.001953125
  },
  "extras_per_seed": [
    {
      "perclass": {
        "cobra": {
          "authentic": 0.5602240896358543,
          "manipulated": 0.18439716312056736,
          "ai_generated": 0.0392156862745098
        },
        "logistic_stacking": {
          "authentic": 0.8235294117647058,
          "manipulated": 0.7878787878787878,
          "ai_generated": 0.9494949494949495
        },
        "daac_gradient_boosting": {
          "authentic": 0.8240740740740741,
          "manipulated": 0.7849462365591398,
          "ai_generated": 0.9595959595959596
        },
        "daac_logistic_regression": {
          "authentic": 0.8252427184466019,
          "manipulated": 0.7897435897435897,
          "ai_generated": 0.9547738693467337
        },
        "daac_mlp": {
          "authentic": 0.8333333333333334,
          "manipulated": 0.81,
          "ai_generated": 0.9591836734693877
        }
      },
      "feature_importances": [
        0.012260963208973408,
        0.0,
        0.0,
        0.0,
        0.024209393188357353,
        0.004113002214580774,
        0.0,
        0.0029252180829644203,
        0.026509776711463928,
        0.0,
        0.0,
        0.0,
        0.00800962746143341,
        0.0,
        0.0,
        0.0,
        0.01959061250090599,
        0.0044047217816114426,
        0.008304914459586143,
        0.004216339439153671,
        0.0015557741280645132,
        0.7013906240463257,
        0.005000877194106579,
        3.8747824874008074e-05,
        0.001187597750686109,
        0.0029460026416927576,
        0.004402345512062311,
        0.014220882207155228,
        0.005608550738543272,
        0.003824959509074688,
        0.004000590182840824,
        0.003964762669056654,
        0.007838351652026176,
        0.0776771605014801,
        0.006535490974783897,
        0.014056921005249023,
        0.004406016319990158,
        0.005124587099999189,
        0.0039050772320479155,
        0.009133388288319111,
        0.003638878231868148,
        0.000747813144698739,
        0.004250002559274435
      ]
    },
    {
      "perclass": {
        "cobra": {
          "authentic": 0.5657142857142857,
          "manipulated": 0.22818791946308725,
          "ai_generated": 0.019801980198019802
        },
        "logistic_stacking": {
          "authentic": 0.7860696517412935,
          "manipulated": 0.7549019607843137,
          "ai_generated": 0.9538461538461539
        },
        "daac_gradient_boosting": {
          "authentic": 0.8041237113402062,
          "manipulated": 0.7922705314009661,
          "ai_generated": 0.9447236180904522
        },
        "daac_logistic_regression": {
          "authentic": 0.7959183673469388,
          "manipulated": 0.780952380952381,
          "ai_generated": 0.9484536082474226
        },
        "daac_mlp": {
          "authentic": 0.7878787878787878,
          "manipulated": 0.7692307692307693,
          "ai_generated": 0.9484536082474226
        }
      },
      "feature_importances": [
        0.1296922117471695,
        0.0,
        0.0,
        0.0,
        0.035734277218580246,
        0.0031644445843994617,
        0.0,
        0.0008311133133247495,
        0.03338554501533508,
        0.0,
        0.0,
        0.0,
        0.0029043748509138823,
        0.0,
        0.0,
        0.0,
        0.01561723742634058,
        0.0043715788051486015,
        0.007375254761427641,
        0.003800653852522373,
        0.0020753967110067606,
        0.5434511303901672,
        0.002580620814114809,
        0.05314215272665024,
        0.0033340188674628735,
        0.0007411681581288576,
        0.004112569149583578,
        0.01715726964175701,
        0.0045063793659210205,
        0.005109850782901049,
        0.003631552215665579,
        0.0040971580892801285,
        0.006897089537233114,
        0.0683949664235115,
        0.005069582257419825,
        0.00984961912035942,
        0.006172035820782185,
        0.005769202020019293,
        0.005354017484933138,
        0.008239755406975746,
        0.0034377959091216326,
        0.0,
        0.0
      ]
    },
    {
      "perclass": {
        "cobra": {
          "authentic": 0.5797101449275363,
          "manipulated": 0.18064516129032257,
          "ai_generated": 0.0
        },
        "logistic_stacking": {
          "authentic": 0.803921568627451,
          "manipulated": 0.7761194029850746,
          "ai_generated": 0.9641025641025641
        },
        "daac_gradient_boosting": {
          "authentic": 0.8275862068965517,
          "manipulated": 0.8020304568527918,
          "ai_generated": 0.98
        },
        "daac_logistic_regression": {
          "authentic": 0.8040201005025126,
          "manipulated": 0.7864077669902912,
          "ai_generated": 0.9641025641025641
        },
        "daac_mlp": {
          "authentic": 0.8040201005025126,
          "manipulated": 0.7864077669902912,
          "ai_generated": 0.9641025641025641
        }
      },
      "feature_importances": [
        0.02496812678873539,
        0.0,
        0.0,
        0.0,
        0.04987386241555214,
        0.0500948466360569,
        0.0,
        0.0015697552589699626,
        0.02161283977329731,
        0.0,
        0.0,
        0.00010614686470944434,
        0.011726115830242634,
        0.0,
        0.0,
        0.0,
        0.006310940720140934,
        0.007172100245952606,
        0.01209541130810976,
        0.004805493168532848,
        0.004364291206002235,
        0.6106090545654297,
        0.000792948470916599,
        0.0009054258116520941,
        0.003338942304253578,
        0.001488590962253511,
        0.005455619189888239,
        0.028132131323218346,
        0.005737317260354757,
        0.006454694550484419,
        0.004984536208212376,
        0.005149644799530506,
        0.014822526834905148,
        0.07200495153665543,
        0.006195675116032362,
        0.009775851853191853,
        0.004823880735784769,
        0.00553657952696085,
        0.006314859259873629,
        0.008543969132006168,
        0.004232840612530708,
        0.0,
        0.0
      ]
    },
    {
      "perclass": {
        "cobra": {
          "authentic": 0.5747126436781609,
          "manipulated": 0.23684210526315788,
          "ai_generated": 0.0
        },
        "logistic_stacking": {
          "authentic": 0.8223350253807107,
          "manipulated": 0.8285714285714286,
          "ai_generated": 0.9533678756476683
        },
        "daac_gradient_boosting": {
          "authentic": 0.7817258883248731,
          "manipulated": 0.7745098039215687,
          "ai_generated": 0.9547738693467337
        },
        "daac_logistic_regression": {
          "authentic": 0.8223350253807107,
          "manipulated": 0.8285714285714286,
          "ai_generated": 0.9533678756476683
        },
        "daac_mlp": {
          "authentic": 0.8223350253807107,
          "manipulated": 0.8285714285714286,
          "ai_generated": 0.9533678756476683
        }
      },
      "feature_importances": [
        0.049832072108983994,
        0.0,
        0.0,
        0.0,
        0.03547623008489609,
        0.0038384830113500357,
        0.0,
        0.006014807149767876,
        0.04667804762721062,
        0.0,
        0.0,
        0.0,
        0.013359184376895428,
        0.0,
        0.0,
        0.0,
        0.012305345386266708,
        0.005087601952254772,
        0.007930261082947254,
        0.0050075543113052845,
        0.008525771088898182,
        0.6351955533027649,
        0.0014945153379812837,
        0.0074861664324998856,
        0.001445893314667046,
        0.0003378746332600713,
        0.0034646678250283003,
        0.017007529735565186,
        0.00578533997759223,
        0.004924332723021507,
        0.004177480470389128,
        0.00412783632054925,
        0.008005297742784023,
        0.0682920590043068,
        0.005876835435628891,
        0.01226673275232315,
        0.006725804880261421,
        0.00537852430716157,
        0.0034580042120069265,
        0.006615259684622288,
        0.0037513673305511475,
        0.0,
        0.00012756876822095364
      ]
    },
    {
      "perclass": {
        "cobra": {
          "authentic": 0.5698005698005698,
          "manipulated": 0.1643835616438356,
          "ai_generated": 0.05825242718446602
        },
        "logistic_stacking": {
          "authentic": 0.7920792079207921,
          "manipulated": 0.7647058823529411,
          "ai_generated": 0.9587628865979382
        },
        "daac_gradient_boosting": {
          "authentic": 0.8133971291866029,
          "manipulated": 0.7853403141361257,
          "ai_generated": 0.97
        },
        "daac_logistic_regression": {
          "authentic": 0.7920792079207921,
          "manipulated": 0.7684729064039408,
          "ai_generated": 0.9641025641025641
        },
        "daac_mlp": {
          "authentic": 0.8080808080808081,
          "manipulated": 0.7922705314009661,
          "ai_generated": 0.9641025641025641
        }
      },
      "feature_importances": [
        0.006894066464155912,
        0.0,
        0.0,
        0.0,
        0.04261567071080208,
        0.004131211433559656,
        0.0,
        0.001825301325879991,
        0.022216176614165306,
        0.0,
        0.0,
        0.0,
        0.00855983141809702,
        0.0,
        0.0,
        0.0,
        0.011880778707563877,
        0.004820729605853558,
        0.010212486609816551,
        0.004110269248485565,
        0.0022516539320349693,
        0.689667284488678,
        0.001749963965266943,
        0.01456004660576582,
        0.000501800503116101,
        0.0,
        0.004490313120186329,
        0.017428411170840263,
        0.005979418288916349,
        0.00573172839358449,
        0.004159066826105118,
        0.005715642124414444,
        0.00822206400334835,
        0.0727517306804657,
        0.006797592621296644,
        0.014019024558365345,
        0.00621912581846118,
        0.005745407659560442,
        0.004990345798432827,
        0.005376813933253288,
        0.0033434852957725525,
        0.0,
        0.0030327243730425835
      ]
    },
    {
      "perclass": {
        "cobra": {
          "authentic": 0.5780346820809249,
          "manipulated": 0.23529411764705882,
          "ai_generated": 0.019801980198019802
        },
        "logistic_stacking": {
          "authentic": 0.7745098039215687,
          "manipulated": 0.746268656716418,
          "ai_generated": 0.9538461538461539
        },
        "daac_gradient_boosting": {
          "authentic": 0.8292682926829268,
          "manipulated": 0.8080808080808081,
          "ai_generated": 0.9644670050761421
        },
        "daac_logistic_regression": {
          "authentic": 0.7959183673469388,
          "manipulated": 0.7904761904761904,
          "ai_generated": 0.9587628865979382
        },
        "daac_mlp": {
          "authentic": 0.8,
          "manipulated": 0.7684729064039408,
          "ai_generated": 0.9441624365482234
        }
      },
      "feature_importances": [
        0.012016321532428265,
        0.0,
        0.0,
        0.0,
        0.025193894281983376,
        0.0010698430705815554,
        0.0,
        0.004216921515762806,
        0.029378289356827736,
        0.0,
        0.0,
        0.0,
        0.007260167505592108,
        0.0,
        0.0,
        0.0,
        0.011003001593053341,
        0.004421615041792393,
        0.006612979806959629,
        0.0032156482338905334,
        0.005835487972944975,
        0.7359851002693176,
        0.0024304601829499006,
        0.0031064751092344522,
        0.0013408714439719915,
        0.00029402232030406594,
        0.003231989685446024,
        0.016050215810537338,
        0.005347315222024918,
        0.004037328064441681,
        0.003764118067920208,
        0.003564082318916917,
        0.00955603551119566,
        0.06593075394630432,
        0.0037939611356705427,
        0.008456780575215816,
        0.004792811349034309,
        0.005275253672152758,
        0.0042368401773273945,
        0.005216014571487904,
        0.003365386975929141,
        0.0,
        0.0
      ]
    },
    {
      "perclass": {
        "cobra": {
          "authentic": 0.5806451612903226,
          "manipulated": 0.1794871794871795,
          "ai_generated": 0.05825242718446602
        },
        "logistic_stacking": {
          "authentic": 0.83,
          "manipulated": 0.8177339901477833,
          "ai_generated": 0.9543147208121827
        },
        "daac_gradient_boosting": {
          "authentic": 0.8656716417910447,
          "manipulated": 0.845771144278607,
          "ai_generated": 0.9696969696969697
        },
        "daac_logistic_regression": {
          "authentic": 0.8235294117647058,
          "manipulated": 0.8040201005025126,
          "ai_generated": 0.9543147208121827
        },
        "daac_mlp": {
          "authentic": 0.8258706467661692,
          "manipulated": 0.8118811881188119,
          "ai_generated": 0.9543147208121827
        }
      },
      "feature_importances": [
        0.4369219243526459,
        0.0,
        0.0,
        0.0,
        0.05479808151721954,
        0.005307518877089024,
        0.0,
        0.010701037012040615,
        0.030440567061305046,
        0.0,
        0.0,
        0.0,
        0.02328355237841606,
        0.0,
        0.0,
        0.0,
        0.012855554930865765,
        0.009180741384625435,
        0.020001674070954323,
        0.008203455246984959,
        0.005772595759481192,
        0.0,
        0.0037750734481960535,
        0.06928879767656326,
        0.0031735182274132967,
        0.0,
        0.00791168212890625,
        0.03578057885169983,
        0.010484213940799236,
        0.0104172732681036,
        0.009545139968395233,
        0.009233631193637848,
        0.015910007059574127,
        0.12297641485929489,
        0.013014255091547966,
        0.017369123175740242,
        0.012411260977387428,
        0.012400188483297825,
        0.013747400604188442,
        0.006551811471581459,
        0.008542969822883606,
        0.0,
        0.0
      ]
    },
    {
      "perclass": {
        "cobra": {
          "authentic": 0.56657223796034,
          "manipulated": 0.1917808219178082,
          "ai_generated": 0.019801980198019802
        },
        "logistic_stacking": {
          "authentic": 0.8140703517587939,
          "manipulated": 0.7920792079207921,
          "ai_generated": 0.9447236180904522
        },
        "daac_gradient_boosting": {
          "authentic": 0.83,
          "manipulated": 0.8059701492537313,
          "ai_generated": 0.964824120603015
        },
        "daac_logistic_regression": {
          "authentic": 0.8247422680412371,
          "manipulated": 0.8115942028985508,
          "ai_generated": 0.9447236180904522
        },
        "daac_mlp": {
          "authentic": 0.8307692307692308,
          "manipulated": 0.8173076923076923,
          "ai_generated": 0.9441624365482234
        }
      },
      "feature_importances": [
        0.007620912045240402,
        0.0,
        0.0,
        0.0,
        0.04628005251288414,
        0.0033133402466773987,
        0.0,
        0.0010787808569148183,
        0.049003686755895615,
        0.0,
        0.0,
        0.0,
        0.006932906806468964,
        0.0,
        0.0,
        0.0,
        0.009008735418319702,
        0.00693700835108757,
        0.010074999183416367,
        0.005120399408042431,
        0.025160303339362144,
        0.543064534664154,
        0.004304005764424801,
        0.06877589225769043,
        0.0003154743171762675,
        0.0,
        0.006362712476402521,
        0.01908634789288044,
        0.007690527476370335,
        0.00580478785559535,
        0.0044243535958230495,
        0.0050424267537891865,
        0.012939965352416039,
        0.10260672122240067,
        0.008730697445571423,
        0.012199975550174713,
        0.006762439850717783,
        0.006176891271024942,
        0.007013100199401379,
        0.0023659290745854378,
        0.005506754387170076,
        0.0002953670045826584,
        0.0
      ]
    },
    {
      "perclass": {
        "cobra": {
          "authentic": 0.559322033898305,
          "manipulated": 0.16666666666666666,
          "ai_generated": 0.0392156862745098
        },
        "logistic_stacking": {
          "authentic": 0.83,
          "manipulated": 0.8159203980099502,
          "ai_generated": 0.9748743718592965
        },
        "daac_gradient_boosting": {
          "authentic": 0.8177339901477833,
          "manipulated": 0.81,
          "ai_generated": 0.9746192893401016
        },
        "daac_logistic_regression": {
          "authentic": 0.8137254901960784,
          "manipulated": 0.797979797979798,
          "ai_generated": 0.9696969696969697
        },
        "daac_mlp": {
          "authentic": 0.8301886792452831,
          "manipulated": 0.8,
          "ai_generated": 0.9696969696969697
        }
      },
      "feature_importances": [
        0.009983634576201439,
        0.0,
        0.0,
        0.0,
        0.041773710399866104,
        0.004019185435026884,
        0.0,
        0.0031896813306957483,
        0.0169173963367939,
        0.0,
        0.0,
        0.0,
        0.006145729683339596,
        0.0,
        0.0,
        0.0,
        0.029630402103066444,
        0.008492293767631054,
        0.01323853712528944,
        0.005688895471394062,
        0.05098765343427658,
        0.5276514887809753,
        0.003263526363298297,
        0.050545405596494675,
        0.0026122990529984236,
        0.011092079803347588,
        0.005576110444962978,
        0.014718178659677505,
        0.007037577219307423,
        0.006764963734894991,
        0.005501205567270517,
        0.005765837151557207,
        0.014310240745544434,
        0.10365124046802521,
        0.009008831344544888,
        0.01291635725647211,
        0.005461493972688913,
        0.007994365878403187,
        0.005066020879894495,
        0.005267851985991001,
        0.005727767013013363,
        0.0,
        0.0
      ]
    },
    {
      "perclass": {
        "cobra": {
          "authentic": 0.5934718100890207,
          "manipulated": 0.2222222222222222,
          "ai_generated": 0.019801980198019802
        },
        "logistic_stacking": {
          "authentic": 0.8140703517587939,
          "manipulated": 0.7902439024390244,
          "ai_generated": 0.9285714285714286
        },
        "daac_gradient_boosting": {
          "authentic": 0.8118811881188119,
          "manipulated": 0.7920792079207921,
          "ai_generated": 0.9489795918367347
        },
        "daac_logistic_regression": {
          "authentic": 0.8241206030150754,
          "manipulated": 0.7961165048543689,
          "ai_generated": 0.9333333333333333
        },
        "daac_mlp": {
          "authentic": 0.8431372549019608,
          "manipulated": 0.8059701492537313,
          "ai_generated": 0.9333333333333333
        }
      },
      "feature_importances": [
        0.0015032899100333452,
        0.0,
        0.0,
        0.0,
        0.038375869393348694,
        0.0017468258738517761,
        0.0,
        0.02120925299823284,
        0.033852141350507736,
        0.0,
        0.0,
        0.0,
        0.00830774288624525,
        0.0,
        0.0,
        0.0,
        0.02886045351624489,
        0.005308735184371471,
        0.009153315797448158,
        0.005260758567601442,
        0.0014192324597388506,
        0.6585288643836975,
        0.003104968462139368,
        0.003346735378727317,
        0.0019509593257680535,
        0.006465869955718517,
        0.004419151693582535,
        0.010572819039225578,
        0.005499882157891989,
        0.0047750878147780895,
        0.005350899882614613,
        0.006475446280092001,
        0.005939667113125324,
        0.07764244824647903,
        0.006180270574986935,
        0.016576137393712997,
        0.0067555466666817665,
        0.007995505817234516,
        0.005697999149560928,
        0.0029751507099717855,
        0.004630978684872389,
        0.0001179614700959064,
        0.0
      ]
    }
  ],
  "tables": {
    "table1_methods": "\n=== Table 1: Method Comparison (macro-F1, 10 seeds) ===\nMethod                                   F1 mean    \u00b1std  p (vs COBRA)\n------------------------------------------------------------------------\nMajority Vote                             0.2774  0.0178  0.0371*  \nWeighted Majority Vote                    0.2664  0.0128  1.0000   \nCOBRA (drwa)                              0.2664  0.0090    \u2014  \nLogistic Stacking (A4+LR)                 0.8500  0.0161  0.0020** \nDAAC-LR  (A5+LR)                          0.8541  0.0087  0.0020** \nDAAC-GBM (A5+GBM)  \u2190 proposed             0.8613  0.0156  0.0020** \nDAAC-MLP (A5+MLP)                         0.8570  0.0122  0.0020** \n\n  *** p<0.001  ** p<0.01  * p<0.05  (Wilcoxon signed-rank, 10 seeds)",
    "table2_perclass": "\n=== Table 2: Per-class F1 (mean over 10 seeds) ===\nMethod                      authentic   manipulated   ai_generated\n-------------------------------------------------------------------\nCOBRA (drwa)                   0.5728         0.1990         0.0274\nLogistic Stacking              0.8091         0.7874         0.9536\nDAAC-GBM (proposed)            0.8205         0.8001         0.9632",
    "table3_ablation": "\n=== Table 3: Feature Group Ablation (GBM, 10 seeds) ===\nAblation                      Dim    GBM F1    \u00b1std\n----------------------------------------------------\nA1  confidence only             4    0.7972  0.0149\nA2  verdict only               16    0.7596  0.0213\nA3  disagreement only          23    0.8534  0.0102\nA4  verdict+confidence         20    0.8506  0.0202\nA5  full DAAC                  43    0.8613  0.0156",
    "table4_feature_importance": "\n=== Table 4: Top-15 GBM Feature Importances (avg 10 seeds) ===\n  Rank  Feature                                       Importance\n  ----------------------------------------------------------------\n  1     disagree_frequency_fatformer                      0.5646\n  2     conflict_frequency_fatformer                      0.0832\n  3     frequency_verdict_authentic                       0.0692\n  4     noise_verdict_authentic                           0.0394\n  5     fatformer_verdict_authentic                       0.0310\n  6     disagree_noise_fatformer                          0.0271\n  7     conf_diff_frequency_fatformer                     0.0190\n  8     frequency_confidence                              0.0157\n  9     conflict_noise_fatformer                          0.0127\n  10    disagree_frequency_noise                          0.0108\n  11    fatformer_confidence                              0.0105\n  12    conflict_frequency_noise                          0.0104\n  13    spatial_verdict_authentic                         0.0096\n  14    noise_verdict_manipulated                         0.0081\n  15    conflict_frequency_spatial                        0.0071"
  }
}