{
  "timestamp": "2026-02-17T14:29:46.415144",
  "mode": "PathA_fixed_dataset_repeated_split",
  "config": "experiments/configs/phase2_patha_scale120_feat_evidence51_oracle_lossaverse_guard.yaml",
  "precollected_jsonl": "experiments/results/phase2_patha_scale120_feat_evidence51_oracle_lossaverse_guard/patha_agent_outputs_20260217_140559.jsonl",
  "collection_seed": 42,
  "split_protocol": {
    "strategy": "kfold",
    "k_folds": 5,
    "test_folds": [
      0,
      1,
      2,
      3,
      4
    ],
    "val_fold_offset": 1,
    "split_seeds": [
      300,
      301,
      302,
      303,
      304
    ]
  },
  "split_seeds": [
    300,
    300,
    300,
    300,
    300,
    301,
    301,
    301,
    301,
    301,
    302,
    302,
    302,
    302,
    302,
    303,
    303,
    303,
    303,
    303,
    304,
    304,
    304,
    304,
    304
  ],
  "n_runs": 25,
  "runs": [
    {
      "split_strategy": "kfold",
      "split_seed": 300,
      "seed": 42,
      "phase1_best": "mlp",
      "phase2_best": "logistic_regression",
      "phase1_best_f1": 0.7825925925925926,
      "phase2_best_f1": 0.802207105064248,
      "f1_diff": 0.019614512471655354,
      "mcnemar_statistic": 0.0,
      "mcnemar_pvalue": 1.0,
      "mcnemar_b": 3,
      "mcnemar_c": 4,
      "n_test_samples": 72,
      "significant": false,
      "elapsed_seconds": 2.5404651165008545,
      "result_path": "experiments/results/phase2_patha_scale120_feat_evidence51_oracle_lossaverse_guard/phase2_patha_results_20260217_142904.json",
      "k_folds": 5,
      "test_fold": 0,
      "val_fold": 1
    },
    {
      "split_strategy": "kfold",
      "split_seed": 300,
      "seed": 42,
      "phase1_best": "gradient_boosting",
      "phase2_best": "logistic_regression",
      "phase1_best_f1": 0.8327342047930283,
      "phase2_best_f1": 0.8606209150326798,
      "f1_diff": 0.027886710239651502,
      "mcnemar_statistic": 0.16666666666666666,
      "mcnemar_pvalue": 0.6830913983096086,
      "mcnemar_b": 2,
      "mcnemar_c": 4,
      "n_test_samples": 72,
      "significant": false,
      "elapsed_seconds": 1.876615047454834,
      "result_path": "experiments/results/phase2_patha_scale120_feat_evidence51_oracle_lossaverse_guard/phase2_patha_results_20260217_142905.json",
      "k_folds": 5,
      "test_fold": 1,
      "val_fold": 2
    },
    {
      "split_strategy": "kfold",
      "split_seed": 300,
      "seed": 42,
      "phase1_best": "gradient_boosting",
      "phase2_best": "hybrid_guard_gradient_boosting",
      "phase1_best_f1": 0.8137533875338754,
      "phase2_best_f1": 0.8137533875338754,
      "f1_diff": 0.0,
      "mcnemar_statistic": 0.0,
      "mcnemar_pvalue": 1.0,
      "mcnemar_b": 0,
      "mcnemar_c": 0,
      "n_test_samples": 72,
      "significant": false,
      "elapsed_seconds": 1.552678108215332,
      "result_path": "experiments/results/phase2_patha_scale120_feat_evidence51_oracle_lossaverse_guard/phase2_patha_results_20260217_142907.json",
      "k_folds": 5,
      "test_fold": 2,
      "val_fold": 3
    },
    {
      "split_strategy": "kfold",
      "split_seed": 300,
      "seed": 42,
      "phase1_best": "mlp",
      "phase2_best": "mlp",
      "phase1_best_f1": 0.7114210190502233,
      "phase2_best_f1": 0.7222242497232462,
      "f1_diff": 0.010803230673022912,
      "mcnemar_statistic": 0.0,
      "mcnemar_pvalue": 1.0,
      "mcnemar_b": 1,
      "mcnemar_c": 2,
      "n_test_samples": 72,
      "significant": false,
      "elapsed_seconds": 1.5451743602752686,
      "result_path": "experiments/results/phase2_patha_scale120_feat_evidence51_oracle_lossaverse_guard/phase2_patha_results_20260217_142909.json",
      "k_folds": 5,
      "test_fold": 3,
      "val_fold": 4
    },
    {
      "split_strategy": "kfold",
      "split_seed": 300,
      "seed": 42,
      "phase1_best": "logistic_regression",
      "phase2_best": "hybrid_guard_logistic_regression",
      "phase1_best_f1": 0.8329826504245109,
      "phase2_best_f1": 0.8329826504245109,
      "f1_diff": 0.0,
      "mcnemar_statistic": 0.0,
      "mcnemar_pvalue": 1.0,
      "mcnemar_b": 0,
      "mcnemar_c": 0,
      "n_test_samples": 72,
      "significant": false,
      "elapsed_seconds": 1.889272689819336,
      "result_path": "experiments/results/phase2_patha_scale120_feat_evidence51_oracle_lossaverse_guard/phase2_patha_results_20260217_142910.json",
      "k_folds": 5,
      "test_fold": 4,
      "val_fold": 0
    },
    {
      "split_strategy": "kfold",
      "split_seed": 301,
      "seed": 42,
      "phase1_best": "logistic_regression",
      "phase2_best": "hybrid_guard_gradient_boosting",
      "phase1_best_f1": 0.8459035788228334,
      "phase2_best_f1": 0.804847494553377,
      "f1_diff": -0.041056084269456394,
      "mcnemar_statistic": 0.36363636363636365,
      "mcnemar_pvalue": 0.5464935954065822,
      "mcnemar_b": 7,
      "mcnemar_c": 4,
      "n_test_samples": 72,
      "significant": false,
      "elapsed_seconds": 1.583272933959961,
      "result_path": "experiments/results/phase2_patha_scale120_feat_evidence51_oracle_lossaverse_guard/phase2_patha_results_20260217_142912.json",
      "k_folds": 5,
      "test_fold": 0,
      "val_fold": 1
    },
    {
      "split_strategy": "kfold",
      "split_seed": 301,
      "seed": 42,
      "phase1_best": "mlp",
      "phase2_best": "hybrid_guard_logistic_regression",
      "phase1_best_f1": 0.8040305010893246,
      "phase2_best_f1": 0.833528521934319,
      "f1_diff": 0.02949802084499442,
      "mcnemar_statistic": 0.16666666666666666,
      "mcnemar_pvalue": 0.6830913983096086,
      "mcnemar_b": 2,
      "mcnemar_c": 4,
      "n_test_samples": 72,
      "significant": false,
      "elapsed_seconds": 1.4460349082946777,
      "result_path": "experiments/results/phase2_patha_scale120_feat_evidence51_oracle_lossaverse_guard/phase2_patha_results_20260217_142914.json",
      "k_folds": 5,
      "test_fold": 1,
      "val_fold": 2
    },
    {
      "split_strategy": "kfold",
      "split_seed": 301,
      "seed": 42,
      "phase1_best": "logistic_regression",
      "phase2_best": "gradient_boosting",
      "phase1_best_f1": 0.8630582667849748,
      "phase2_best_f1": 0.9038405797101449,
      "f1_diff": 0.040782312925170094,
      "mcnemar_statistic": 0.4444444444444444,
      "mcnemar_pvalue": 0.5049850750938457,
      "mcnemar_b": 3,
      "mcnemar_c": 6,
      "n_test_samples": 72,
      "significant": false,
      "elapsed_seconds": 1.4994947910308838,
      "result_path": "experiments/results/phase2_patha_scale120_feat_evidence51_oracle_lossaverse_guard/phase2_patha_results_20260217_142915.json",
      "k_folds": 5,
      "test_fold": 2,
      "val_fold": 3
    },
    {
      "split_strategy": "kfold",
      "split_seed": 301,
      "seed": 42,
      "phase1_best": "gradient_boosting",
      "phase2_best": "hybrid_guard_mlp",
      "phase1_best_f1": 0.8333333333333334,
      "phase2_best_f1": 0.8217384731670446,
      "f1_diff": -0.011594860166288745,
      "mcnemar_statistic": 0.0,
      "mcnemar_pvalue": 1.0,
      "mcnemar_b": 3,
      "mcnemar_c": 2,
      "n_test_samples": 72,
      "significant": false,
      "elapsed_seconds": 1.5177066326141357,
      "result_path": "experiments/results/phase2_patha_scale120_feat_evidence51_oracle_lossaverse_guard/phase2_patha_results_20260217_142917.json",
      "k_folds": 5,
      "test_fold": 3,
      "val_fold": 4
    },
    {
      "split_strategy": "kfold",
      "split_seed": 301,
      "seed": 42,
      "phase1_best": "gradient_boosting",
      "phase2_best": "hybrid_guard_gradient_boosting",
      "phase1_best_f1": 0.8597584541062803,
      "phase2_best_f1": 0.8171023965141612,
      "f1_diff": -0.0426560575921191,
      "mcnemar_statistic": 0.4444444444444444,
      "mcnemar_pvalue": 0.5049850750938457,
      "mcnemar_b": 6,
      "mcnemar_c": 3,
      "n_test_samples": 72,
      "significant": false,
      "elapsed_seconds": 1.5440359115600586,
      "result_path": "experiments/results/phase2_patha_scale120_feat_evidence51_oracle_lossaverse_guard/phase2_patha_results_20260217_142918.json",
      "k_folds": 5,
      "test_fold": 4,
      "val_fold": 0
    },
    {
      "split_strategy": "kfold",
      "split_seed": 302,
      "seed": 42,
      "phase1_best": "logistic_regression",
      "phase2_best": "logistic_regression",
      "phase1_best_f1": 0.8096145124716553,
      "phase2_best_f1": 0.8226757369614512,
      "f1_diff": 0.013061224489795964,
      "mcnemar_statistic": 0.0,
      "mcnemar_pvalue": 1.0,
      "mcnemar_b": 1,
      "mcnemar_c": 2,
      "n_test_samples": 72,
      "significant": false,
      "elapsed_seconds": 1.690277338027954,
      "result_path": "experiments/results/phase2_patha_scale120_feat_evidence51_oracle_lossaverse_guard/phase2_patha_results_20260217_142920.json",
      "k_folds": 5,
      "test_fold": 0,
      "val_fold": 1
    },
    {
      "split_strategy": "kfold",
      "split_seed": 302,
      "seed": 42,
      "phase1_best": "mlp",
      "phase2_best": "hybrid_guard_logistic_regression",
      "phase1_best_f1": 0.7735691772236623,
      "phase2_best_f1": 0.8032955404383976,
      "f1_diff": 0.02972636321473532,
      "mcnemar_statistic": 0.25,
      "mcnemar_pvalue": 0.6170750774519739,
      "mcnemar_b": 1,
      "mcnemar_c": 3,
      "n_test_samples": 72,
      "significant": false,
      "elapsed_seconds": 2.5273232460021973,
      "result_path": "experiments/results/phase2_patha_scale120_feat_evidence51_oracle_lossaverse_guard/phase2_patha_results_20260217_142922.json",
      "k_folds": 5,
      "test_fold": 1,
      "val_fold": 2
    },
    {
      "split_strategy": "kfold",
      "split_seed": 302,
      "seed": 42,
      "phase1_best": "gradient_boosting",
      "phase2_best": "gradient_boosting",
      "phase1_best_f1": 0.859591836734694,
      "phase2_best_f1": 0.8997233622131023,
      "f1_diff": 0.04013152547840837,
      "mcnemar_statistic": 0.8,
      "mcnemar_pvalue": 0.37109336952269756,
      "mcnemar_b": 1,
      "mcnemar_c": 4,
      "n_test_samples": 72,
      "significant": false,
      "elapsed_seconds": 1.696070909500122,
      "result_path": "experiments/results/phase2_patha_scale120_feat_evidence51_oracle_lossaverse_guard/phase2_patha_results_20260217_142924.json",
      "k_folds": 5,
      "test_fold": 2,
      "val_fold": 3
    },
    {
      "split_strategy": "kfold",
      "split_seed": 302,
      "seed": 42,
      "phase1_best": "logistic_regression",
      "phase2_best": "gradient_boosting",
      "phase1_best_f1": 0.7510065263351411,
      "phase2_best_f1": 0.7938485909319016,
      "f1_diff": 0.04284206459676054,
      "mcnemar_statistic": 0.4444444444444444,
      "mcnemar_pvalue": 0.5049850750938457,
      "mcnemar_b": 3,
      "mcnemar_c": 6,
      "n_test_samples": 72,
      "significant": false,
      "elapsed_seconds": 1.9837062358856201,
      "result_path": "experiments/results/phase2_patha_scale120_feat_evidence51_oracle_lossaverse_guard/phase2_patha_results_20260217_142926.json",
      "k_folds": 5,
      "test_fold": 3,
      "val_fold": 4
    },
    {
      "split_strategy": "kfold",
      "split_seed": 302,
      "seed": 42,
      "phase1_best": "gradient_boosting",
      "phase2_best": "hybrid_guard_gradient_boosting",
      "phase1_best_f1": 0.8361204013377926,
      "phase2_best_f1": 0.8361204013377926,
      "f1_diff": 0.0,
      "mcnemar_statistic": 0.0,
      "mcnemar_pvalue": 1.0,
      "mcnemar_b": 0,
      "mcnemar_c": 0,
      "n_test_samples": 72,
      "significant": false,
      "elapsed_seconds": 2.030393123626709,
      "result_path": "experiments/results/phase2_patha_scale120_feat_evidence51_oracle_lossaverse_guard/phase2_patha_results_20260217_142928.json",
      "k_folds": 5,
      "test_fold": 4,
      "val_fold": 0
    },
    {
      "split_strategy": "kfold",
      "split_seed": 303,
      "seed": 42,
      "phase1_best": "logistic_regression",
      "phase2_best": "gradient_boosting",
      "phase1_best_f1": 0.8225257417182106,
      "phase2_best_f1": 0.889261519477584,
      "f1_diff": 0.06673577775937345,
      "mcnemar_statistic": 2.2857142857142856,
      "mcnemar_pvalue": 0.13057001811573693,
      "mcnemar_b": 1,
      "mcnemar_c": 6,
      "n_test_samples": 72,
      "significant": false,
      "elapsed_seconds": 1.6322269439697266,
      "result_path": "experiments/results/phase2_patha_scale120_feat_evidence51_oracle_lossaverse_guard/phase2_patha_results_20260217_142930.json",
      "k_folds": 5,
      "test_fold": 0,
      "val_fold": 1
    },
    {
      "split_strategy": "kfold",
      "split_seed": 303,
      "seed": 42,
      "phase1_best": "gradient_boosting",
      "phase2_best": "hybrid_guard_gradient_boosting",
      "phase1_best_f1": 0.7496135265700482,
      "phase2_best_f1": 0.7899622071050643,
      "f1_diff": 0.04034868053501606,
      "mcnemar_statistic": 0.8,
      "mcnemar_pvalue": 0.37109336952269756,
      "mcnemar_b": 1,
      "mcnemar_c": 4,
      "n_test_samples": 72,
      "significant": false,
      "elapsed_seconds": 2.3115217685699463,
      "result_path": "experiments/results/phase2_patha_scale120_feat_evidence51_oracle_lossaverse_guard/phase2_patha_results_20260217_142932.json",
      "k_folds": 5,
      "test_fold": 1,
      "val_fold": 2
    },
    {
      "split_strategy": "kfold",
      "split_seed": 303,
      "seed": 42,
      "phase1_best": "logistic_regression",
      "phase2_best": "hybrid_guard_logistic_regression",
      "phase1_best_f1": 0.8881400966183576,
      "phase2_best_f1": 0.8881400966183576,
      "f1_diff": 0.0,
      "mcnemar_statistic": 0.0,
      "mcnemar_pvalue": 1.0,
      "mcnemar_b": 0,
      "mcnemar_c": 0,
      "n_test_samples": 72,
      "significant": false,
      "elapsed_seconds": 1.8364503383636475,
      "result_path": "experiments/results/phase2_patha_scale120_feat_evidence51_oracle_lossaverse_guard/phase2_patha_results_20260217_142934.json",
      "k_folds": 5,
      "test_fold": 2,
      "val_fold": 3
    },
    {
      "split_strategy": "kfold",
      "split_seed": 303,
      "seed": 42,
      "phase1_best": "mlp",
      "phase2_best": "mlp",
      "phase1_best_f1": 0.7942648368180283,
      "phase2_best_f1": 0.8201798141396552,
      "f1_diff": 0.025914977321626953,
      "mcnemar_statistic": 0.5,
      "mcnemar_pvalue": 0.47950012218695337,
      "mcnemar_b": 0,
      "mcnemar_c": 2,
      "n_test_samples": 72,
      "significant": false,
      "elapsed_seconds": 1.6838891506195068,
      "result_path": "experiments/results/phase2_patha_scale120_feat_evidence51_oracle_lossaverse_guard/phase2_patha_results_20260217_142936.json",
      "k_folds": 5,
      "test_fold": 3,
      "val_fold": 4
    },
    {
      "split_strategy": "kfold",
      "split_seed": 303,
      "seed": 42,
      "phase1_best": "mlp",
      "phase2_best": "mlp",
      "phase1_best_f1": 0.7906432748538013,
      "phase2_best_f1": 0.8055740125507568,
      "f1_diff": 0.01493073769695552,
      "mcnemar_statistic": 0.0,
      "mcnemar_pvalue": 1.0,
      "mcnemar_b": 2,
      "mcnemar_c": 3,
      "n_test_samples": 72,
      "significant": false,
      "elapsed_seconds": 1.8534235954284668,
      "result_path": "experiments/results/phase2_patha_scale120_feat_evidence51_oracle_lossaverse_guard/phase2_patha_results_20260217_142938.json",
      "k_folds": 5,
      "test_fold": 4,
      "val_fold": 0
    },
    {
      "split_strategy": "kfold",
      "split_seed": 304,
      "seed": 42,
      "phase1_best": "gradient_boosting",
      "phase2_best": "hybrid_guard_gradient_boosting",
      "phase1_best_f1": 0.7759866357890673,
      "phase2_best_f1": 0.7759866357890673,
      "f1_diff": 0.0,
      "mcnemar_statistic": 0.0,
      "mcnemar_pvalue": 1.0,
      "mcnemar_b": 0,
      "mcnemar_c": 0,
      "n_test_samples": 72,
      "significant": false,
      "elapsed_seconds": 1.6302070617675781,
      "result_path": "experiments/results/phase2_patha_scale120_feat_evidence51_oracle_lossaverse_guard/phase2_patha_results_20260217_142939.json",
      "k_folds": 5,
      "test_fold": 0,
      "val_fold": 1
    },
    {
      "split_strategy": "kfold",
      "split_seed": 304,
      "seed": 42,
      "phase1_best": "gradient_boosting",
      "phase2_best": "hybrid_guard_gradient_boosting",
      "phase1_best_f1": 0.7556710114544405,
      "phase2_best_f1": 0.8157488169531527,
      "f1_diff": 0.06007780549871222,
      "mcnemar_statistic": 2.25,
      "mcnemar_pvalue": 0.13361440253771584,
      "mcnemar_b": 0,
      "mcnemar_c": 4,
      "n_test_samples": 72,
      "significant": false,
      "elapsed_seconds": 1.8450040817260742,
      "result_path": "experiments/results/phase2_patha_scale120_feat_evidence51_oracle_lossaverse_guard/phase2_patha_results_20260217_142941.json",
      "k_folds": 5,
      "test_fold": 1,
      "val_fold": 2
    },
    {
      "split_strategy": "kfold",
      "split_seed": 304,
      "seed": 42,
      "phase1_best": "gradient_boosting",
      "phase2_best": "hybrid_guard_gradient_boosting",
      "phase1_best_f1": 0.8329251700680272,
      "phase2_best_f1": 0.8489349537121517,
      "f1_diff": 0.01600978364412442,
      "mcnemar_statistic": 0.0,
      "mcnemar_pvalue": 1.0,
      "mcnemar_b": 1,
      "mcnemar_c": 2,
      "n_test_samples": 72,
      "significant": false,
      "elapsed_seconds": 1.6304552555084229,
      "result_path": "experiments/results/phase2_patha_scale120_feat_evidence51_oracle_lossaverse_guard/phase2_patha_results_20260217_142943.json",
      "k_folds": 5,
      "test_fold": 2,
      "val_fold": 3
    },
    {
      "split_strategy": "kfold",
      "split_seed": 304,
      "seed": 42,
      "phase1_best": "logistic_regression",
      "phase2_best": "hybrid_guard_logistic_regression",
      "phase1_best_f1": 0.7546296296296297,
      "phase2_best_f1": 0.7546296296296297,
      "f1_diff": 0.0,
      "mcnemar_statistic": 0.0,
      "mcnemar_pvalue": 1.0,
      "mcnemar_b": 0,
      "mcnemar_c": 0,
      "n_test_samples": 72,
      "significant": false,
      "elapsed_seconds": 1.5302379131317139,
      "result_path": "experiments/results/phase2_patha_scale120_feat_evidence51_oracle_lossaverse_guard/phase2_patha_results_20260217_142944.json",
      "k_folds": 5,
      "test_fold": 3,
      "val_fold": 4
    },
    {
      "split_strategy": "kfold",
      "split_seed": 304,
      "seed": 42,
      "phase1_best": "gradient_boosting",
      "phase2_best": "gradient_boosting",
      "phase1_best_f1": 0.8331393586712735,
      "phase2_best_f1": 0.8586161737422241,
      "f1_diff": 0.025476815070950565,
      "mcnemar_statistic": 0.5,
      "mcnemar_pvalue": 0.47950012218695337,
      "mcnemar_b": 0,
      "mcnemar_c": 2,
      "n_test_samples": 72,
      "significant": false,
      "elapsed_seconds": 1.672961711883545,
      "result_path": "experiments/results/phase2_patha_scale120_feat_evidence51_oracle_lossaverse_guard/phase2_patha_results_20260217_142946.json",
      "k_folds": 5,
      "test_fold": 4,
      "val_fold": 0
    }
  ],
  "aggregate": {
    "phase1_best_f1_mean": 0.8082803889929923,
    "phase1_best_f1_std": 0.042581977573274164,
    "phase2_best_f1_mean": 0.8246217306103157,
    "phase2_best_f1_std": 0.04258965866678054,
    "f1_diff_mean": 0.016341341617323576,
    "f1_diff_std": 0.0258976329711178,
    "f1_diff_min": -0.0426560575921191,
    "f1_diff_max": 0.06673577775937345,
    "significant_count": 0,
    "positive_count": 16,
    "negative_count": 3,
    "zero_count": 6,
    "sign_test_pvalue": 0.004425048828125,
    "negative_rate": 0.12,
    "downside_mean": 0.0038122800811145694,
    "cvar_downside": 0.03176900067595475,
    "cvar_f1_diff": -0.03176900067595475,
    "worst_case_loss": 0.0426560575921191,
    "downside_cvar_alpha": 0.1,
    "pooled_mcnemar_b": 38,
    "pooled_mcnemar_c": 67,
    "pooled_mcnemar_statistic": 7.466666666666667,
    "pooled_mcnemar_pvalue": 0.006285181643384481,
    "pooled_mcnemar_significant": true
  }
}